odoo/addons/purchase_invoice_new_picking_line/README.rst
odoo/addons/purchase_invoice_new_picking_line/__init__.py
odoo/addons/purchase_invoice_new_picking_line/__manifest__.py
odoo/addons/purchase_invoice_new_picking_line/i18n/it.po
odoo/addons/purchase_invoice_new_picking_line/i18n/purchase_invoice_new_picking_line.pot
odoo/addons/purchase_invoice_new_picking_line/models/__init__.py
odoo/addons/purchase_invoice_new_picking_line/models/purchase_order.py
odoo/addons/purchase_invoice_new_picking_line/readme/CONTRIBUTORS.rst
odoo/addons/purchase_invoice_new_picking_line/readme/DESCRIPTION.rst
odoo/addons/purchase_invoice_new_picking_line/static/description/icon.png
odoo/addons/purchase_invoice_new_picking_line/static/description/index.html
odoo/addons/purchase_invoice_new_picking_line/tests/__init__.py
odoo/addons/purchase_invoice_new_picking_line/tests/test_invoice.py
odoo_addon_purchase_invoice_new_picking_line-16.0.1.0.0.7.dist-info/METADATA
odoo_addon_purchase_invoice_new_picking_line-16.0.1.0.0.7.dist-info/WHEEL
odoo_addon_purchase_invoice_new_picking_line-16.0.1.0.0.7.dist-info/top_level.txt
odoo_addon_purchase_invoice_new_picking_line-16.0.1.0.0.7.dist-info/RECORD
