Metadata-Version: 2.1
Name: odoo-addon-purchase_invoice_new_picking_line
Version: 16.0.1.0.0.7
Summary: When creating an invoice from a purchase order, this module also adds invoice lines for products that were in the order's pickings but not in the order itself.
Home-page: https://github.com/OCA/purchase-workflow
Author: Coop IT Easy SCRLfs, Odoo Community Association (OCA)
Author-email: support@odoo-community.org
License: AGPL-3
Classifier: Programming Language :: Python
Classifier: Framework :: Odoo
Classifier: Framework :: Odoo :: 16.0
Classifier: License :: OSI Approved :: GNU Affero General Public License v3
Requires-Python: >=3.10
Requires-Dist: odoo<16.1dev,>=16.0a
